{
  "name": "PancakeSwap Default List",
  "timestamp": "2021-03-17T09:56:23Z",
  "version": {
    "major": 2,
    "minor": 10,
    "patch": 0
  },
  "tags": {},
  "logoURI": "https://exchange.pancakeswap.finance/images/pancakeswap.png",
  "keywords": ["pancake", "default"],
  "tokens": [
    {
      "name": "PNFT Token",
      "symbol": "PNFT",
      "address": "0x10401b9A7E93E10aC92E7bB55Ae87433B9E01e08",
      "chainId": 8007736,
      "decimals": 18,
      "logoURI": "https://ipfs.io/ipfs/Qmbk5oRJXvC51Yxy9A26S3YvNkn7xgFdzWpF7gzs4H6mhU"
    }
  ]
}
